periodictable/__init__.py
periodictable/activation.dat
periodictable/activation.py
periodictable/constants.py
periodictable/core.py
periodictable/covalent_radius.py
periodictable/cromermann.py
periodictable/crystal_structure.py
periodictable/density.py
periodictable/f0_WaasKirf.dat
periodictable/fasta.py
periodictable/formulas.py
periodictable/magnetic_ff.py
periodictable/mass.py
periodictable/mass_2001.py
periodictable/nsf.py
periodictable/nsf_tables.py
periodictable/plot.py
periodictable/util.py
periodictable/xsf.py
periodictable/xsf/ac.nff
periodictable/xsf/ag.nff
periodictable/xsf/al.nff
periodictable/xsf/ar.nff
periodictable/xsf/as.nff
periodictable/xsf/at.nff
periodictable/xsf/au.nff
periodictable/xsf/b.nff
periodictable/xsf/ba.nff
periodictable/xsf/be.nff
periodictable/xsf/bi.nff
periodictable/xsf/br.nff
periodictable/xsf/c.nff
periodictable/xsf/ca.nff
periodictable/xsf/cd.nff
periodictable/xsf/ce.nff
periodictable/xsf/cl.nff
periodictable/xsf/co.nff
periodictable/xsf/cr.nff
periodictable/xsf/cs.nff
periodictable/xsf/cu.nff
periodictable/xsf/dy.nff
periodictable/xsf/er.nff
periodictable/xsf/eu.nff
periodictable/xsf/f.nff
periodictable/xsf/fe.nff
periodictable/xsf/fr.nff
periodictable/xsf/ga.nff
periodictable/xsf/gd.nff
periodictable/xsf/ge.nff
periodictable/xsf/h.nff
periodictable/xsf/he.nff
periodictable/xsf/hf.nff
periodictable/xsf/hg.nff
periodictable/xsf/ho.nff
periodictable/xsf/i.nff
periodictable/xsf/in.nff
periodictable/xsf/ir.nff
periodictable/xsf/k.nff
periodictable/xsf/kr.nff
periodictable/xsf/la.nff
periodictable/xsf/li.nff
periodictable/xsf/lu.nff
periodictable/xsf/mg.nff
periodictable/xsf/mn.nff
periodictable/xsf/mo.nff
periodictable/xsf/n.nff
periodictable/xsf/na.nff
periodictable/xsf/nb.nff
periodictable/xsf/nd.nff
periodictable/xsf/ne.nff
periodictable/xsf/ni.nff
periodictable/xsf/o.nff
periodictable/xsf/os.nff
periodictable/xsf/p.nff
periodictable/xsf/pa.nff
periodictable/xsf/pb.nff
periodictable/xsf/pd.nff
periodictable/xsf/pm.nff
periodictable-2.0.0.dist-info/LICENSE.txt
periodictable-2.0.0.dist-info/METADATA
periodictable-2.0.0.dist-info/WHEEL
periodictable-2.0.0.dist-info/top_level.txt
periodictable-2.0.0.dist-info/RECORD
