Metadata-Version: 2.1
Name: periodictable
Version: 2.0.0
Summary: Extensible periodic table of the elements
Author-email: Paul Kienzle <paul.kienzle@nist.gov>
License: Periodictable is in the public domain.
Project-URL: documentation, https://periodictable.readthedocs.io
Project-URL: repository, https://github.com/pkienzle/periodictable
Classifier: Development Status :: 5 - Production/Stable
Classifier: Environment :: Console
Classifier: Intended Audience :: Science/Research
Classifier: License :: Public Domain
Classifier: Operating System :: OS Independent
Classifier: Programming Language :: Python
Classifier: Programming Language :: Python :: 3
Classifier: Topic :: Scientific/Engineering :: Chemistry
Classifier: Topic :: Scientific/Engineering :: Physics
Requires-Python: >=3.8
License-File: LICENSE.txt
Requires-Dist: pyparsing
Requires-Dist: numpy
Provides-Extra: dev
Requires-Dist: build; extra == "dev"
Requires-Dist: pytest; extra == "dev"
Requires-Dist: pytest-cov; extra == "dev"
Requires-Dist: matplotlib; extra == "dev"
Requires-Dist: sphinx; extra == "dev"
